QuotaEngine-1.1.4.dist-info/DESCRIPTION.rst
QuotaEngine-1.1.4.dist-info/METADATA
QuotaEngine-1.1.4.dist-info/RECORD
QuotaEngine-1.1.4.dist-info/WHEEL
QuotaEngine-1.1.4.dist-info/metadata.json
QuotaEngine-1.1.4.dist-info/top_level.txt
qEngine/__init__.py
qEngine/gui.py
qEngine/main.py
qEngine/miscFunctions.py
qEngine/qEngine.py
qEngine/questionClass.py
qEngine/quotaGroupClass.py
qEngine/quotaSoupClass.py
qEngine/tabWidgetClass.py
qEngine/tableWidgetClass.py
