Metadata-Version: 2.0
Name: QuotaEngine
Version: 1.1.4
Summary: A quota editor
Home-page: UNKNOWN
Author: Artem Dubrovskiy
Author-email: ad13box@gmail.com
License: UNKNOWN
Keywords: quota editor dimensions unicom intelligence utility
Platform: UNKNOWN
Classifier: Programming Language :: Python :: 3.4
Requires-Dist: PyQt5
Requires-Dist: bs4
